instavizlib/__init__.py
instavizlib/core.py
instavizlib-1.0.3.dist-info/licenses/LICENSE
instavizlib-1.0.3.dist-info/METADATA
instavizlib-1.0.3.dist-info/WHEEL
instavizlib-1.0.3.dist-info/top_level.txt
instavizlib-1.0.3.dist-info/RECORD
