Metadata-Version: 2.4
Name: instavizlib
Version: 1.0.3
Summary: Intelligent Data Visualization - See truth, not just charts. Auto-selects best charts, provides insights, and creates beautiful visualizations.
Author-email: "Md. Ujayer Hasnat" <dev.ujayerhasnat@gmail.com>
Maintainer-email: "Md. Ujayer Hasnat" <dev.ujayerhasnat@gmail.com>
License: MIT
Project-URL: Homepage, https://github.com/CodexUjayer/
Project-URL: Documentation, https://github.com/CodexUjayer/instaviz#readme
Project-URL: Repository, https://github.com/CodexUjayer/instaviz
Project-URL: Bug Tracker, https://github.com/CodexUjayer/instaviz/issues
Project-URL: LinkedIn, https://linkedin.com/in/ujayerhasnat
Keywords: visualization,matplotlib,pandas,data-visualization,eda,exploratory-data-analysis,plotting,charts,dataviz,auto-visualization,smart-charts,data-science
Classifier: Development Status :: 4 - Beta
Classifier: Intended Audience :: Developers
Classifier: Intended Audience :: Science/Research
Classifier: License :: OSI Approved :: MIT License
Classifier: Operating System :: OS Independent
Classifier: Programming Language :: Python :: 3
Classifier: Programming Language :: Python :: 3.8
Classifier: Programming Language :: Python :: 3.9
Classifier: Programming Language :: Python :: 3.10
Classifier: Programming Language :: Python :: 3.11
Classifier: Programming Language :: Python :: 3.12
Classifier: Topic :: Scientific/Engineering :: Visualization
Classifier: Topic :: Scientific/Engineering :: Information Analysis
Requires-Python: >=3.8
License-File: LICENSE
Requires-Dist: numpy>=1.20.0
Requires-Dist: pandas>=1.3.0
Requires-Dist: matplotlib>=3.5.0
Requires-Dist: scipy>=1.7.0
Provides-Extra: dev
Requires-Dist: pytest>=7.0.0; extra == "dev"
Requires-Dist: black>=22.0.0; extra == "dev"
Requires-Dist: isort>=5.0.0; extra == "dev"
Requires-Dist: twine>=4.0.0; extra == "dev"
Requires-Dist: build>=0.7.0; extra == "dev"
Dynamic: license-file
